{
    "swagger": "2.0",
    "info": {
        "contact": {}
    },
    "paths": {
        "/v1/core/login": {
            "post": {
                "description": "corp登录",
                "consumes": [
                    "application/json"
                ],
                "produces": [
                    "application/json"
                ],
                "tags": [
                    "corp"
                ],
                "summary": "corp登录",
                "parameters": [
                    {
                        "description": "login",
                        "name": "login",
                        "in": "body",
                        "required": true,
                        "schema": {
                            "$ref": "#/definitions/corp.LoginReq"
                        }
                    }
                ],
                "responses": {
                    "200": {
                        "description": "OK",
                        "schema": {
                            "$ref": "#/definitions/corp.UserLoginResp"
                        }
                    }
                }
            }
        }
    },
    "definitions": {
        "corp.LoginReq": {
            "type": "object",
            "required": [
                "mobile",
                "password"
            ],
            "properties": {
                "mobile": {
                    "type": "string"
                },
                "password": {
                    "type": "string"
                }
            }
        },
        "corp.UserLoginResp": {
            "type": "object",
            "properties": {
                "mobile": {
                    "type": "integer"
                },
                "name": {
                    "type": "string"
                },
                "token": {
                    "type": "string"
                }
            }
        }
    }
}